doit/__init__.py
doit/__main__.py
doit/action.py
doit/api.py
doit/cmd_auto.py
doit/cmd_base.py
doit/cmd_clean.py
doit/cmd_completion.py
doit/cmd_dumpdb.py
doit/cmd_forget.py
doit/cmd_help.py
doit/cmd_ignore.py
doit/cmd_info.py
doit/cmd_list.py
doit/cmd_resetdep.py
doit/cmd_run.py
doit/cmd_strace.py
doit/cmdparse.py
doit/compat.py
doit/control.py
doit/dependency.py
doit/doit_cmd.py
doit/exceptions.py
doit/filewatch.py
doit/globals.py
doit/loader.py
doit/plugin.py
doit/reporter.py
doit/runner.py
doit/task.py
doit/tools.py
doit/version.py
doit-0.35.0.dist-info/AUTHORS
doit-0.35.0.dist-info/LICENSE
doit-0.35.0.dist-info/METADATA
doit-0.35.0.dist-info/WHEEL
doit-0.35.0.dist-info/entry_points.txt
doit-0.35.0.dist-info/top_level.txt
doit-0.35.0.dist-info/RECORD
