Metadata-Version: 2.1
Name: doit
Version: 0.35.0
Summary: doit - Automation Tool
Home-page: http://pydoit.org
Author: Eduardo Naufel Schettino
Author-email: schettino72@gmail.com
License: MIT
Project-URL: Documentation, https://pydoit.org/
Project-URL: Source, https://github.com/pydoit/doit/
Project-URL: Tracker, https://github.com/pydoit/doit/issues
Keywords: build make task automation pipeline task-runner
Platform: UNKNOWN
Classifier: Development Status :: 5 - Production/Stable
Classifier: Environment :: Console
Classifier: License :: OSI Approved :: MIT License
Classifier: Natural Language :: English
Classifier: Operating System :: OS Independent
Classifier: Operating System :: POSIX
Classifier: Programming Language :: Python :: 3
Classifier: Programming Language :: Python :: 3.8
Classifier: Programming Language :: Python :: 3.9
Classifier: Programming Language :: Python :: 3.10
Classifier: Intended Audience :: Developers
Classifier: Intended Audience :: Information Technology
Classifier: Intended Audience :: Science/Research
Classifier: Intended Audience :: System Administrators
Classifier: Topic :: Software Development :: Build Tools
Classifier: Topic :: Software Development :: Testing
Classifier: Topic :: Software Development :: Quality Assurance
Classifier: Topic :: Scientific/Engineering
Requires-Python: >=3.8
Requires-Dist: cloudpickle
Requires-Dist: macfsevents ; sys.platform == "darwin"
Requires-Dist: pyinotify ; sys.platform == "linux"
Provides-Extra: plugins
Requires-Dist: setuptools ; extra == 'plugins'
Provides-Extra: toml
Requires-Dist: toml (>=0.10.1) ; extra == 'toml'
